{"dataProyects" : [
  {
    "id": "0",
    "title": "Gamers Components",
    "img": "/gamers-components.webp",
    "description":
      "Proyecto simulando una tienda E-commerce de componentes de computadora",
    "deploy": "https://lauutigomez.github.io/GamersComponents-proyecto/",
    "repo": "https://github.com/LauutiGomez/GamersComponents-proyecto.git",
    "tags": [
      {
        "id":"1",
        "label":"HTML",
        "imageUrl":"/html5.svg",
        "classTechnology":"html"
      },
      {
        "id":"2",
        "label":"CSS",
        "imageUrl":"/css.svg",
        "classTechnology":"css"
      },
      {
        "id":"3",
        "label":"JavaScript",
        "imageUrl":"/javascript.svg",
        "classTechnology":"JavaScript"
      }
    ]
  },
  {
    "id": "4",
    "title": "ToDo List",
    "img": "/ToDo-List.webp",
    "description": "Aplicacion para organizar una lista de tareas a realizar",
    "deploy": "https://lauutigomez.github.io/ToDo-List/",
    "repo": "https://github.com/LauutiGomez/ToDo-List",
    "tags": 
    [{
      "id":"5",
      "label":"React",
      "imageUrl":"/react.svg",
      "classTechnology":"React"
    },
    {
      "id":"6",
      "label":"Tailwind CSS",
      "imageUrl":"/tailwindcss.svg",
      "classTechnology":"Tailwind"
    }]
  }
]
}

